randomcsv/CategoryColumn.py
randomcsv/Column.py
randomcsv/CsvGenerator.py
randomcsv/FileUtils.py
randomcsv/IntColumn.py
randomcsv/RandomNumberColumn.py
randomcsv/StringColumn.py
randomcsv/__init__.py
randomcsv/resources/__init__.py
randomcsv/resources/__pycache__/__init__.cpython-37.pyc
randomcsv/resources/dictionaries/__init__.py
randomcsv/resources/dictionaries/firstNames.txt
randomcsv/resources/dictionaries/__pycache__/__init__.cpython-37.pyc
spider/NameSpider.py
spider/__init__.py
randomcsv-0.1.3.dist-info/LICENSE.txt
randomcsv-0.1.3.dist-info/METADATA
randomcsv-0.1.3.dist-info/WHEEL
randomcsv-0.1.3.dist-info/top_level.txt
randomcsv-0.1.3.dist-info/RECORD
