Metadata-Version: 2.1
Name: randomcsv
Version: 0.1.3
Summary: For generating specific CSVs for testing data piplines
Home-page: https://github.com/PhilipBuhr/randomCsv
Author: Philip Buhr
Author-email: philip.buhr@buhrwerk.de
License: MIT
Download-URL: https://github.com/PhilipBuhr/randomCsv/archive/0.1.0.tar.gz
Platform: UNKNOWN
Classifier: Programming Language :: Python :: 3
Classifier: License :: OSI Approved :: MIT License
Classifier: Operating System :: OS Independent
Requires-Python: >=3.6
Requires-Dist: pandas
Requires-Dist: requests
Requires-Dist: pytest
Requires-Dist: numpy
